sql_library/__init__.py
sql_library/sql_library.py
sql_library-0.6.dist-info/METADATA
sql_library-0.6.dist-info/WHEEL
sql_library-0.6.dist-info/top_level.txt
sql_library-0.6.dist-info/RECORD
