Metadata-Version: 2.2
Name: sql_library
Version: 0.6
Summary: A simple library for working with PostgreSQL
Author: Alexey Kalinin
Author-email: kad2005@list.ru
Classifier: Programming Language :: Python :: 3
Classifier: License :: OSI Approved :: MIT License
Classifier: Operating System :: OS Independent
Requires-Python: >=3.6
Requires-Dist: psycopg2
Dynamic: author
Dynamic: author-email
Dynamic: classifier
Dynamic: description-content-type
Dynamic: requires-dist
Dynamic: requires-python
Dynamic: summary
